fmp_py/__init__.py
fmp_py/fmp_base.py
fmp_py/fmp_chart_data.py
fmp_py/fmp_company_information.py
fmp_py/fmp_company_search.py
fmp_py/fmp_crypto.py
fmp_py/fmp_dividends.py
fmp_py/fmp_earnings.py
fmp_py/fmp_financial_statements.py
fmp_py/fmp_forex.py
fmp_py/fmp_historical_data.py
fmp_py/fmp_ipo_calendar.py
fmp_py/fmp_mergers_and_aquisitions.py
fmp_py/fmp_price_targets.py
fmp_py/fmp_quote.py
fmp_py/fmp_splits.py
fmp_py/fmp_statement_analysis.py
fmp_py/fmp_stock_list.py
fmp_py/fmp_upgrades_downgrades.py
fmp_py/fmp_valuation.py
fmp_py/models/company_information.py
fmp_py/models/price_targets.py
fmp_py/models/quote.py
fmp_py/models/statement_analysis.py
fmp_py/models/upgrades_downgrades.py
fmp_py/models/valuation.py
fmp_py-0.0.20.3.dist-info/LICENSE
fmp_py-0.0.20.3.dist-info/METADATA
fmp_py-0.0.20.3.dist-info/WHEEL
fmp_py-0.0.20.3.dist-info/RECORD
