Metadata-Version: 2.1
Name: fmp-py
Version: 0.0.20.3
Summary: Python package for Financial Modeling Prep API
Home-page: https://pypi.org/project/fmp-py/
Author: TexasCoding
Author-email: jeff10278@me.com
Requires-Python: >=3.10,<4.0
Classifier: Programming Language :: Python :: 3
Classifier: Programming Language :: Python :: 3.10
Classifier: Programming Language :: Python :: 3.11
Classifier: Programming Language :: Python :: 3.12
Requires-Dist: pandas (>=2.2.2,<3.0.0)
Requires-Dist: pendulum (>=3.0.0,<4.0.0)
Requires-Dist: python-dotenv (>=1.0.1,<2.0.0)
Requires-Dist: requests (>=2.32.3,<3.0.0)
Requires-Dist: requests-cache (>=1.2.1,<2.0.0)
Requires-Dist: requests-mock (>=1.12.1,<2.0.0)
Requires-Dist: requests-ratelimiter (>=0.7.0,<0.8.0)
Requires-Dist: ta (>=0.11.0,<0.12.0)
Project-URL: Documentation, https://fmp-py.readthedocs.io/en/latest/index.html
Project-URL: Repository, https://github.com/TexasCoding/fmp-py
